einar/__init__.py
einar/__main__.py
einar/cli.py
einar/exceptions.py
einar/helpers.py
einar/version.py
einar/warning.py
einar-2.0.0.dist-info/licenses/LICENSE
einar-2.0.0.dist-info/METADATA
einar-2.0.0.dist-info/WHEEL
einar-2.0.0.dist-info/entry_points.txt
einar-2.0.0.dist-info/top_level.txt
einar-2.0.0.dist-info/RECORD
